photonqat/Fock.py
photonqat/Gaussian.py
photonqat/__init__.py
photonqat/opt.py
photonqat/Fockbase/WignerFunc.py
photonqat/Fockbase/__init__.py
photonqat/Fockbase/bosonicLadder.py
photonqat/Fockbase/gateOps.py
photonqat/Fockbase/gates.py
photonqat/Fockbase/stateOps.py
photonqat/Fockbase/states.py
photonqat/Gaussianformula/__init__.py
photonqat/Gaussianformula/baseFunc.py
photonqat/Gaussianformula/gateOps.py
photonqat/Gaussianformula/gates.py
photonqat/Gaussianformula/ordering.py
photonqat-0.2.3.dist-info/LICENSE
photonqat-0.2.3.dist-info/METADATA
photonqat-0.2.3.dist-info/WHEEL
photonqat-0.2.3.dist-info/top_level.txt
photonqat-0.2.3.dist-info/RECORD
